{
  "overall": {
    "tp": 223,
    "fp": 248,
    "fn": 149,
    "tn": 1507
  },
  "per_category": {
    "구조": {
      "tp": 37,
      "fp": 54,
      "fn": 5,
      "tn": 146
    },
    "공정성": {
      "tp": 50,
      "fp": 49,
      "fn": 54,
      "tn": 402
    },
    "적법성": {
      "tp": 28,
      "fp": 32,
      "fn": 23,
      "tn": 504
    },
    "거버넌스": {
      "tp": 50,
      "fp": 53,
      "fn": 42,
      "tn": 336
    },
    "효율성": {
      "tp": 58,
      "fp": 60,
      "fn": 25,
      "tn": 119
    }
  },
  "meta": {
    "backend": "linear",
    "verdict_rows": 2394,
    "f1_notes": {
      "구조": 0.556,
      "공정성": 0.493,
      "적법성": 0.505,
      "거버넌스": 0.513,
      "효율성": 0.577,
      "total": 0.529
    },
    "baseline_f1": {
      "구조": 0.475,
      "공정성": 0.455,
      "적법성": 0.435,
      "거버넌스": 0.496,
      "효율성": 0.366,
      "total": 0.457
    }
  }
}